<?xml version="1.0" encoding="UTF-8"?>
<flow id="5f3264e3-31cf-42a6-b825-adec27621429">
  <descriptionCdata><![CDATA[5f3264e3-31cf-42a6-b825-adec27621429.0f9f8502-c376-4d39-ad16-ce475779b063.description=This workflow returns the component properties and values using Artifact APIs.\n\nresult\:\npropertyNameValuesList\: pipe separated list of property name and values ( where each property name and values would be ; seprated and multiple values would be , seprated)\ne.g. - property 1; value1,value2|property 2; value3|property 3; value3,value4|........
5f3264e3-31cf-42a6-b825-adec27621429.1b4d53a4-0b74-4fbb-bf54-b2b3fea071c4.description=This workflow updates the Process Instance State using PEM API.\n\nInputs\:\n_PROCESS_INSTANCE_ID - Process Instance Id\n_processInstanceState - Process Instance State (Use value from selection list CSA-ProcessInstance-State)\n\n\n\nResult\:\n_processInstanceState -Updated Process Instance State\n
5f3264e3-31cf-42a6-b825-adec27621429.3358f7c2-1c36-45a6-9d7a-607a68c459fa.prompt=User Identifier
5f3264e3-31cf-42a6-b825-adec27621429.60a11f3f-f75d-446d-aa16-49dd39c62db8.prompt=User Identifier
5f3264e3-31cf-42a6-b825-adec27621429.c63beae9-2697-47a8-8c74-63b03a9b78eb.description=This workflow updates the Process Instance State using PEM API.\n\nInputs\:\n_PROCESS_INSTANCE_ID - Process Instance Id\n_processInstanceState - Process Instance State (Use value from selection list CSA-ProcessInstance-State)\n\n\n\nResult\:\n_processInstanceState -Updated Process Instance State\n
5f3264e3-31cf-42a6-b825-adec27621429.c7383804-b394-4c91-bc90-b42a2d188749.prompt=Process Instance ID
5f3264e3-31cf-42a6-b825-adec27621429.cc2d774a-da62-40c1-9bf1-186524784a4c.prompt=User Identifier
5f3264e3-31cf-42a6-b825-adec27621429.de698889-7c65-480c-abac-2efee5121f16.prompt=Process Instance ID
5f3264e3-31cf-42a6-b825-adec27621429.ed767c64-46fc-4687-8972-9c5b9a4dba9e.description=<pre>This is an operation that does nothing. It can be used for filtering flow variables by feeding them in as inputs and filtering them on the results tab.\n\nResponses\:\n    success\n    failure\n</pre>
]]></descriptionCdata>
  <annotation></annotation>
  <name>Set Up SSH Key on server V4</name>
  <categories/>
  <inputs>
    <staticBinding id="1166e0dd-e42a-418d-8ecb-7d906c43207c">
      <annotation></annotation>
      <assignFromContext>true</assignFromContext>
      <assignToContext>true</assignToContext>
      <inputType>STRING</inputType>
      <isList>false</isList>
      <required>false</required>
      <isPersisted>true</isPersisted>
      <inputSymbol>CSA_CONTEXT_ID</inputSymbol>
      <listDelimiter>,</listDelimiter>
      <value></value>
      <record>false</record>
    </staticBinding>
    <staticBinding id="3d79f208-55ad-4426-8e41-67f6cd26743a">
      <annotation></annotation>
      <assignFromContext>true</assignFromContext>
      <assignToContext>true</assignToContext>
      <inputType>STRING</inputType>
      <isList>false</isList>
      <required>false</required>
      <isPersisted>true</isPersisted>
      <inputSymbol>CSA_PROCESS_ID</inputSymbol>
      <listDelimiter>,</listDelimiter>
      <value></value>
      <record>false</record>
    </staticBinding>
    <staticBinding id="55e7cdea-70d1-4e9b-b263-ace3745f305a">
      <annotation></annotation>
      <assignFromContext>true</assignFromContext>
      <assignToContext>true</assignToContext>
      <inputType>STRING</inputType>
      <isList>false</isList>
      <required>false</required>
      <isPersisted>true</isPersisted>
      <inputSymbol>RSC_PROVIDER_ID</inputSymbol>
      <listDelimiter>,</listDelimiter>
      <value>[TOKEN:RSC_PROVIDER_ID]</value>
      <record>false</record>
    </staticBinding>
    <staticBinding id="483442d9-7dd6-4a7b-93c4-4f5449d83f1e">
      <annotation></annotation>
      <assignFromContext>true</assignFromContext>
      <assignToContext>true</assignToContext>
      <inputType>STRING</inputType>
      <isList>false</isList>
      <required>false</required>
      <isPersisted>true</isPersisted>
      <inputSymbol>RSC_POOL_ID</inputSymbol>
      <listDelimiter>,</listDelimiter>
      <value>[TOKEN:RSC_POOL_ID]</value>
      <record>false</record>
    </staticBinding>
    <staticBinding id="76760026-8c61-4d64-a520-209ac5e3de5e">
      <annotation></annotation>
      <assignFromContext>true</assignFromContext>
      <assignToContext>true</assignToContext>
      <inputType>STRING</inputType>
      <isList>false</isList>
      <required>false</required>
      <isPersisted>true</isPersisted>
      <inputSymbol>RSC_SUBSCRIPTION_ID</inputSymbol>
      <listDelimiter>,</listDelimiter>
      <value>[TOKEN:RSC_SUBSCRIPTION_ID]</value>
      <record>false</record>
    </staticBinding>
    <staticBinding id="857ce633-20e4-4aed-adce-3bc6706c9597">
      <annotation></annotation>
      <assignFromContext>true</assignFromContext>
      <assignToContext>true</assignToContext>
      <inputType>STRING</inputType>
      <isList>false</isList>
      <required>false</required>
      <isPersisted>true</isPersisted>
      <inputSymbol>SVC_INSTANCE_ID</inputSymbol>
      <listDelimiter>,</listDelimiter>
      <value>[TOKEN:SVC_INSTANCE_ID]</value>
      <record>false</record>
    </staticBinding>
    <staticBinding id="854735bb-7aa7-4d4a-b3c4-dd289422aab0">
      <annotation></annotation>
      <assignFromContext>true</assignFromContext>
      <assignToContext>true</assignToContext>
      <inputType>STRING</inputType>
      <isList>false</isList>
      <required>false</required>
      <isPersisted>true</isPersisted>
      <inputSymbol>SVC_COMPONENT_ID</inputSymbol>
      <listDelimiter>,</listDelimiter>
      <value>[TOKEN:SVC_COMPONENT_ID]</value>
      <record>false</record>
    </staticBinding>
    <staticBinding id="a056fca8-f92e-4438-ae7e-47a3d3221250">
      <annotation></annotation>
      <assignFromContext>true</assignFromContext>
      <assignToContext>true</assignToContext>
      <inputType>STRING</inputType>
      <isList>false</isList>
      <required>false</required>
      <isPersisted>true</isPersisted>
      <inputSymbol>SVC_COMPONENT_TYPE</inputSymbol>
      <listDelimiter>,</listDelimiter>
      <value>[TOKEN:SVC_COMPONENT_TYPE]</value>
      <record>false</record>
    </staticBinding>
    <staticBinding id="80ad4254-0b21-4c09-a30c-957326e484e7">
      <annotation></annotation>
      <assignFromContext>true</assignFromContext>
      <assignToContext>true</assignToContext>
      <inputType>STRING</inputType>
      <isList>false</isList>
      <required>false</required>
      <isPersisted>true</isPersisted>
      <inputSymbol>SVC_SUBSCRIPTION_ID</inputSymbol>
      <listDelimiter>,</listDelimiter>
      <value>[TOKEN:SVC_SUBSCRIPTION_ID]</value>
      <record>false</record>
    </staticBinding>
    <staticBinding id="320ad6b7-962a-424e-a4b7-18ab18855f2c">
      <annotation></annotation>
      <assignFromContext>true</assignFromContext>
      <assignToContext>true</assignToContext>
      <inputType>STRING</inputType>
      <isList>false</isList>
      <required>false</required>
      <isPersisted>true</isPersisted>
      <inputSymbol>SVC_SUBSCRIPTION_EMAIL</inputSymbol>
      <listDelimiter>,</listDelimiter>
      <value>[TOKEN:SVC_SUBSCRIPTION_EMAIL]</value>
      <record>false</record>
    </staticBinding>
    <staticBinding id="02eec548-8601-4b84-b6da-f45c79e59caf">
      <annotation></annotation>
      <assignFromContext>true</assignFromContext>
      <assignToContext>true</assignToContext>
      <inputType>STRING</inputType>
      <isList>false</isList>
      <required>false</required>
      <isPersisted>true</isPersisted>
      <inputSymbol>PRN_COMPONENT_ID</inputSymbol>
      <listDelimiter>,</listDelimiter>
      <value>[TOKEN:PRN_COMPONENT_ID]</value>
      <record>false</record>
    </staticBinding>
    <staticBinding id="054e545f-a1ea-40bb-8ccb-31118ed4c4e4">
      <annotation></annotation>
      <assignFromContext>true</assignFromContext>
      <assignToContext>true</assignToContext>
      <inputType>STRING</inputType>
      <isList>false</isList>
      <required>false</required>
      <isPersisted>true</isPersisted>
      <inputSymbol>REQ_ORG_ID</inputSymbol>
      <listDelimiter>,</listDelimiter>
      <value>[TOKEN:REQ_ORG_ID]</value>
      <record>false</record>
    </staticBinding>
    <staticBinding id="68742c33-0b6b-48b2-a570-e9cbc5317124">
      <annotation></annotation>
      <assignFromContext>true</assignFromContext>
      <assignToContext>true</assignToContext>
      <inputType>STRING</inputType>
      <isList>false</isList>
      <required>false</required>
      <isPersisted>true</isPersisted>
      <inputSymbol>REQ_USER_ID</inputSymbol>
      <listDelimiter>,</listDelimiter>
      <value>[TOKEN:REQ_USER_ID]</value>
      <record>false</record>
    </staticBinding>
    <staticBinding id="a30c8c61-0b64-46c4-9777-8b05af195c25">
      <annotation></annotation>
      <assignFromContext>true</assignFromContext>
      <assignToContext>true</assignToContext>
      <inputType>STRING</inputType>
      <isList>false</isList>
      <required>false</required>
      <isPersisted>true</isPersisted>
      <inputSymbol>USR_ORG_ID</inputSymbol>
      <listDelimiter>,</listDelimiter>
      <value>[TOKEN:USR_ORG_ID]</value>
      <record>false</record>
    </staticBinding>
    <staticBinding id="09bf14ea-cdb2-4452-a33b-fc2cd1a01e89">
      <annotation></annotation>
      <assignFromContext>true</assignFromContext>
      <assignToContext>true</assignToContext>
      <inputType>STRING</inputType>
      <isList>false</isList>
      <required>false</required>
      <isPersisted>true</isPersisted>
      <inputSymbol>RSC_BINDING_ID</inputSymbol>
      <listDelimiter>,</listDelimiter>
      <value>[TOKEN:RSC_BINDING_ID]</value>
      <record>false</record>
    </staticBinding>
  </inputs>
  <possibleResponses>
    <opResponse id="17b82bba-e188-4a91-879b-a06d1270209c">
      <annotation></annotation>
      <name>success</name>
      <isDefault>true</isDefault>
      <onFailure>false</onFailure>
      <type>RESOLVED</type>
      <matchRules/>
    </opResponse>
    <opResponse id="17e8cc20-a8a8-4653-ba4c-4ee91916518e">
      <annotation></annotation>
      <name>failure</name>
      <isDefault>false</isDefault>
      <onFailure>true</onFailure>
      <type>ERROR</type>
      <matchRules/>
    </opResponse>
  </possibleResponses>
  <availableResultExpressions/>
  <resultExpression id="44361c29-588c-44ed-a592-4486cad0160b">
    <annotation></annotation>
    <name>FailureMessage</name>
    <fieldName>FailureMessage</fieldName>
    <sourceType>RAWRESULT</sourceType>
    <filters/>
  </resultExpression>
  <iconSpec id="4ebb0ba9-6a69-4345-8073-25b9cf3474fb">
    <baseIcon>flow.png</baseIcon>
    <basePath>System</basePath>
    <readOnly>false</readOnly>
    <layers/>
  </iconSpec>
  <callouts/>
  <checkPointFlow>true</checkPointFlow>
  <compatibleRuntimeContext>false</compatibleRuntimeContext>
  <historyCheckPointFlow>true</historyCheckPointFlow>
  <steps>
    <step id="2228153e-0cd2-4645-b03b-e33d1710ecdb">
      <annotation></annotation>
      <name>Get User Identifier</name>
      <bounds>
        <x>87.0</x>
        <y>67.0</y>
      </bounds>
      <layer>-1</layer>
      <hideInbound>false</hideInbound>
      <addResultToRunContext>false</addResultToRunContext>
      <isCriticalStep>false</isCriticalStep>
      <isNonBlocking>false</isNonBlocking>
      <isParallelStep>false</isParallelStep>
      <isSingleResponse>false</isSingleResponse>
      <recordInHistory>false</recordInHistory>
      <recordRawOutput>false</recordRawOutput>
      <recordPrimaryOutput>false</recordPrimaryOutput>
      <checkPointStep>true</checkPointStep>
      <historyCheckPointStep>true</historyCheckPointStep>
      <scriptResultStep>false</scriptResultStep>
      <userPrompt></userPrompt>
      <bindings>
        <userInputBinding id="152b5ed8-cfb0-49a4-a7da-b4fea1f89e8d">
          <annotation></annotation>
          <fromContextKey>CSA_OO_USER</fromContextKey>
          <assignFromContext>true</assignFromContext>
          <assignToContext>true</assignToContext>
          <inputType>STRING</inputType>
          <isList>false</isList>
          <required>true</required>
          <isPersisted>true</isPersisted>
          <inputSymbol>csaUser</inputSymbol>
          <listDelimiter>,</listDelimiter>
          <record>false</record>
          <prompt></prompt>
          <isMultiSelect>false</isMultiSelect>
          <sourceDelimiter>|</sourceDelimiter>
        </userInputBinding>
      </bindings>
      <transitions>
        <transition id="7f7389b2-3926-4921-8174-b3129a9d26dd">
          <annotation></annotation>
          <name>failure</name>
          <command>NEXT</command>
          <linkMode>false</linkMode>
          <responseSymbol>failure</responseSymbol>
          <shouldHandoff>false</shouldHandoff>
          <transitionValue>0.0</transitionValue>
          <destination>
            <refId>1b4d53a4-0b74-4fbb-bf54-b2b3fea071c4</refId>
          </destination>
          <source>
            <refId>2228153e-0cd2-4645-b03b-e33d1710ecdb</refId>
          </source>
          <positions>
            <point>
              <x>176.0</x>
              <y>161.0</y>
            </point>
            <point>
              <x>393.0</x>
              <y>265.0</y>
            </point>
          </positions>
          <labelPosition>
            <x>333.0</x>
            <y>0.0</y>
          </labelPosition>
        </transition>
        <transition id="4e04abc8-3011-4fcf-b904-372cbdcc1585">
          <annotation></annotation>
          <name>success</name>
          <command>NEXT</command>
          <linkMode>false</linkMode>
          <responseSymbol>success</responseSymbol>
          <shouldHandoff>false</shouldHandoff>
          <transitionValue>0.0</transitionValue>
          <destination>
            <refId>0f9f8502-c376-4d39-ad16-ce475779b063</refId>
          </destination>
          <source>
            <refId>2228153e-0cd2-4645-b03b-e33d1710ecdb</refId>
          </source>
          <positions>
            <point>
              <x>137.0</x>
              <y>101.0</y>
            </point>
            <point>
              <x>136.0</x>
              <y>516.0</y>
            </point>
          </positions>
          <labelPosition>
            <x>333.0</x>
            <y>0.0</y>
          </labelPosition>
        </transition>
      </transitions>
      <properties/>
      <opRef>
        <refId>f1c8b14a-694f-4a03-a84a-c7504fe0a29b</refId>
      </opRef>
      <assignments>
        <flowVariableAssignment id="ab109cd7-c5e4-4478-a6ec-a0f858eb633f">
          <annotation></annotation>
          <name>assignment</name>
          <action>OVERWRITE</action>
          <assignmentTargetType>FLOW_VARIABLE</assignmentTargetType>
          <contextKey>userIdentifier</contextKey>
          <expression id="e9be5f84-47aa-4738-85bc-84a145ac734d">
            <annotation></annotation>
            <name>Result Field: userIdentifier</name>
            <fieldName>userIdentifier</fieldName>
            <sourceType>RAWRESULT</sourceType>
            <filters/>
          </expression>
        </flowVariableAssignment>
      </assignments>
      <throttleSize>0</throttleSize>
    </step>
    <step id="ed767c64-46fc-4687-8972-9c5b9a4dba9e">
      <annotation>5f3264e3-31cf-42a6-b825-adec27621429.ed767c64-46fc-4687-8972-9c5b9a4dba9e.description</annotation>
      <name>Valid SSH Keys Exist</name>
      <bounds>
        <x>488.0</x>
        <y>485.0</y>
      </bounds>
      <layer>-1</layer>
      <hideInbound>false</hideInbound>
      <iconSpec id="8af3329c-de45-4949-b970-5ab028fdadef">
        <baseIcon>astrologer.png</baseIcon>
        <basePath>/Others/</basePath>
        <readOnly>false</readOnly>
        <layers/>
      </iconSpec>
      <addResultToRunContext>false</addResultToRunContext>
      <isCriticalStep>false</isCriticalStep>
      <isNonBlocking>false</isNonBlocking>
      <isParallelStep>false</isParallelStep>
      <isSingleResponse>false</isSingleResponse>
      <recordInHistory>false</recordInHistory>
      <recordRawOutput>true</recordRawOutput>
      <recordPrimaryOutput>true</recordPrimaryOutput>
      <checkPointStep>true</checkPointStep>
      <historyCheckPointStep>true</historyCheckPointStep>
      <scriptResultStep>false</scriptResultStep>
      <userPrompt></userPrompt>
      <scriptlet id="960ea60a-ea50-4133-8d68-eedaf9dfdfbd">
        <annotation></annotation>
        <name>Step Valid SSH Keys Exist in Flow Set Up SSH Key on server V4 (ed767c64-46fc-4687-8972-9c5b9a4dba9e)</name>
        <script>var re = /^Valid ([0-9]) key\(s\) - ([^\s]+)$/;
var result = [];
if( keyValidation !== undefined &amp;&amp; (result = re.exec(keyValidation)) !== null ) {
    var count = parseInt(result[1]);
    var filename = result[2];
    scriptletContext.put(&quot;count&quot;,count);
    scriptletContext.put(&quot;filename&quot;,filename);
    scriptletResponse=&quot;Yes&quot;;
}
else {
    scriptletResponse=&quot;No&quot;;
}
</script>
        <type>NASHORN</type>
      </scriptlet>
      <bindings>
        <userInputBinding id="ecedee81-b1a6-4139-828d-4d6698e9027d">
          <annotation></annotation>
          <assignFromContext>true</assignFromContext>
          <assignToContext>false</assignToContext>
          <inputType>STRING</inputType>
          <isList>false</isList>
          <required>false</required>
          <isPersisted>true</isPersisted>
          <inputSymbol>keyValidation</inputSymbol>
          <listDelimiter>,</listDelimiter>
          <record>false</record>
          <prompt></prompt>
          <isMultiSelect>false</isMultiSelect>
          <sourceDelimiter>|</sourceDelimiter>
        </userInputBinding>
      </bindings>
      <transitions>
        <transition id="02453096-5d62-467f-8917-2f22edbb767b">
          <annotation></annotation>
          <name>No</name>
          <command>NEXT</command>
          <linkMode>false</linkMode>
          <responseSymbol>No</responseSymbol>
          <shouldHandoff>false</shouldHandoff>
          <transitionValue>0.0</transitionValue>
          <destination>
            <refId>c63beae9-2697-47a8-8c74-63b03a9b78eb</refId>
          </destination>
          <source>
            <refId>ed767c64-46fc-4687-8972-9c5b9a4dba9e</refId>
          </source>
          <positions>
            <point>
              <x>330.0</x>
              <y>468.19891500904157</y>
            </point>
            <point>
              <x>971.0</x>
              <y>786.0</y>
            </point>
            <point>
              <x>860.0</x>
              <y>123.0</y>
            </point>
          </positions>
          <labelPosition>
            <x>390.5579582170212</x>
            <y>4.265572760324313</y>
          </labelPosition>
        </transition>
        <transition id="f0bd06d3-b4bd-40dc-8c5c-da0749fd5aa6">
          <annotation></annotation>
          <name>Yes</name>
          <command>NEXT</command>
          <linkMode>false</linkMode>
          <responseSymbol>Yes</responseSymbol>
          <shouldHandoff>false</shouldHandoff>
          <transitionValue>0.0</transitionValue>
          <destination>
            <refId>9d7f897c-8fba-4e95-9e6b-9ec693ca5599</refId>
          </destination>
          <source>
            <refId>ed767c64-46fc-4687-8972-9c5b9a4dba9e</refId>
          </source>
          <positions>
            <point>
              <x>538.0</x>
              <y>519.0</y>
            </point>
            <point>
              <x>770.0</x>
              <y>519.0</y>
            </point>
          </positions>
          <labelPosition>
            <x>333.0</x>
            <y>0.0</y>
          </labelPosition>
        </transition>
      </transitions>
      <properties/>
      <opRef>
        <refId>49e201ef-3e5f-450f-9ce5-86c2cd285070</refId>
      </opRef>
      <assignments/>
      <throttleSize>0</throttleSize>
    </step>
    <returnStep id="c5964227-e3bc-44a4-8371-16464abfb13b">
      <annotation></annotation>
      <name>Resolved : success</name>
      <bounds>
        <x>1222.0</x>
        <y>67.0</y>
      </bounds>
      <layer>-1</layer>
      <hideInbound>false</hideInbound>
      <addResultToRunContext>false</addResultToRunContext>
      <isCriticalStep>false</isCriticalStep>
      <isNonBlocking>false</isNonBlocking>
      <isParallelStep>false</isParallelStep>
      <isSingleResponse>false</isSingleResponse>
      <recordInHistory>false</recordInHistory>
      <recordRawOutput>true</recordRawOutput>
      <recordPrimaryOutput>true</recordPrimaryOutput>
      <checkPointStep>true</checkPointStep>
      <historyCheckPointStep>true</historyCheckPointStep>
      <scriptResultStep>false</scriptResultStep>
      <userPrompt></userPrompt>
      <bindings/>
      <transitions>
        <transition id="9bc1d285-55a6-4317-9f23-c32523b7135e">
          <annotation></annotation>
          <name>return</name>
          <command>NEXT</command>
          <linkMode>false</linkMode>
          <responseSymbol>success</responseSymbol>
          <shouldHandoff>false</shouldHandoff>
          <transitionValue>0.0</transitionValue>
          <destination>
            <refId>c5964227-e3bc-44a4-8371-16464abfb13b</refId>
          </destination>
          <source>
            <refId>c5964227-e3bc-44a4-8371-16464abfb13b</refId>
          </source>
          <positions/>
        </transition>
      </transitions>
      <properties/>
      <returnStepType>RESOLVED</returnStepType>
      <assignments/>
    </returnStep>
    <step id="9d7f897c-8fba-4e95-9e6b-9ec693ca5599">
      <annotation></annotation>
      <name>Apply SSH Keys on Server V4</name>
      <bounds>
        <x>736.0</x>
        <y>488.0</y>
      </bounds>
      <layer>-1</layer>
      <hideInbound>false</hideInbound>
      <addResultToRunContext>false</addResultToRunContext>
      <isCriticalStep>false</isCriticalStep>
      <isNonBlocking>false</isNonBlocking>
      <isParallelStep>false</isParallelStep>
      <isSingleResponse>false</isSingleResponse>
      <recordInHistory>false</recordInHistory>
      <recordRawOutput>true</recordRawOutput>
      <recordPrimaryOutput>true</recordPrimaryOutput>
      <checkPointStep>true</checkPointStep>
      <historyCheckPointStep>true</historyCheckPointStep>
      <scriptResultStep>false</scriptResultStep>
      <userPrompt></userPrompt>
      <bindings>
        <userInputBinding id="9d15b84f-c03e-4f3d-94f0-447f84666ae9">
          <annotation></annotation>
          <fromContextKey>filename</fromContextKey>
          <assignFromContext>true</assignFromContext>
          <assignToContext>false</assignToContext>
          <inputType>STRING</inputType>
          <isList>false</isList>
          <required>false</required>
          <isPersisted>true</isPersisted>
          <inputSymbol>filename</inputSymbol>
          <listDelimiter>,</listDelimiter>
          <record>false</record>
          <prompt></prompt>
          <isMultiSelect>false</isMultiSelect>
          <sourceDelimiter>|</sourceDelimiter>
        </userInputBinding>
        <userInputBinding id="ae692885-c6a8-464e-b3f2-94621dc82582">
          <annotation></annotation>
          <assignFromContext>true</assignFromContext>
          <assignToContext>false</assignToContext>
          <inputType>STRING</inputType>
          <isList>false</isList>
          <required>false</required>
          <isPersisted>true</isPersisted>
          <inputSymbol>hostName</inputSymbol>
          <listDelimiter>,</listDelimiter>
          <record>false</record>
          <prompt></prompt>
          <isMultiSelect>false</isMultiSelect>
          <sourceDelimiter>|</sourceDelimiter>
        </userInputBinding>
        <userInputBinding id="089d927c-c112-4dca-820b-5472a25433a4">
          <annotation></annotation>
          <assignFromContext>true</assignFromContext>
          <assignToContext>false</assignToContext>
          <inputType>STRING</inputType>
          <isList>false</isList>
          <required>false</required>
          <isPersisted>true</isPersisted>
          <inputSymbol>ipAddress</inputSymbol>
          <listDelimiter>,</listDelimiter>
          <record>false</record>
          <prompt></prompt>
          <isMultiSelect>false</isMultiSelect>
          <sourceDelimiter>|</sourceDelimiter>
        </userInputBinding>
        <staticBinding id="d266d359-f81b-4e47-9b1d-e8a2db38cc33">
          <annotation></annotation>
          <assignFromContext>false</assignFromContext>
          <assignToContext>false</assignToContext>
          <inputType>STRING</inputType>
          <isList>false</isList>
          <required>false</required>
          <isPersisted>true</isPersisted>
          <inputSymbol>Max</inputSymbol>
          <listDelimiter>,</listDelimiter>
          <value>10</value>
          <record>false</record>
        </staticBinding>
        <staticBinding id="b4612c17-2c23-46b2-b0c4-2adbe563b544">
          <annotation></annotation>
          <assignFromContext>false</assignFromContext>
          <assignToContext>false</assignToContext>
          <inputType>STRING</inputType>
          <isList>false</isList>
          <required>false</required>
          <isPersisted>true</isPersisted>
          <inputSymbol>waitTime</inputSymbol>
          <listDelimiter>,</listDelimiter>
          <value>60</value>
          <record>false</record>
        </staticBinding>
      </bindings>
      <transitions>
        <transition id="c23cd9f8-6978-4689-9036-fb2c0992b6d6">
          <annotation></annotation>
          <name>failure</name>
          <command>NEXT</command>
          <linkMode>false</linkMode>
          <responseSymbol>failure</responseSymbol>
          <shouldHandoff>false</shouldHandoff>
          <transitionValue>0.0</transitionValue>
          <destination>
            <refId>1b4d53a4-0b74-4fbb-bf54-b2b3fea071c4</refId>
          </destination>
          <source>
            <refId>9d7f897c-8fba-4e95-9e6b-9ec693ca5599</refId>
          </source>
          <positions>
            <point>
              <x>786.0</x>
              <y>522.0</y>
            </point>
            <point>
              <x>542.0</x>
              <y>297.0</y>
            </point>
          </positions>
          <labelPosition>
            <x>333.0</x>
            <y>0.0</y>
          </labelPosition>
        </transition>
        <transition id="cbc8c534-f864-4263-acfe-d6ab06e04e7c">
          <annotation></annotation>
          <name>success</name>
          <command>NEXT</command>
          <linkMode>false</linkMode>
          <responseSymbol>success</responseSymbol>
          <shouldHandoff>false</shouldHandoff>
          <transitionValue>0.0</transitionValue>
          <destination>
            <refId>c63beae9-2697-47a8-8c74-63b03a9b78eb</refId>
          </destination>
          <source>
            <refId>9d7f897c-8fba-4e95-9e6b-9ec693ca5599</refId>
          </source>
          <positions>
            <point>
              <x>786.0</x>
              <y>522.0</y>
            </point>
            <point>
              <x>980.0</x>
              <y>101.0</y>
            </point>
          </positions>
          <labelPosition>
            <x>333.0</x>
            <y>0.0</y>
          </labelPosition>
        </transition>
      </transitions>
      <properties/>
      <opRef>
        <refId>b85257e3-d210-4134-b97d-14b991ba178c</refId>
      </opRef>
      <assignments>
        <flowVariableAssignment id="3f46d355-c031-46cd-88c9-003edc89503a">
          <annotation></annotation>
          <name>assignment</name>
          <action>OVERWRITE</action>
          <assignmentTargetType>FLOW_VARIABLE</assignmentTargetType>
          <contextKey>FailureMessage</contextKey>
          <expression id="c07dc76d-8fe6-4daa-bcd2-28a931ac6126">
            <annotation></annotation>
            <name>Result Field: FailureMessage</name>
            <fieldName>FailureMessage</fieldName>
            <sourceType>RAWRESULT</sourceType>
            <filters/>
          </expression>
        </flowVariableAssignment>
      </assignments>
      <throttleSize>0</throttleSize>
    </step>
    <returnStep id="1f33ddc1-9218-42f5-8d19-f31bb7f014c2">
      <annotation></annotation>
      <name>Error : failure</name>
      <bounds>
        <x>492.0</x>
        <y>67.0</y>
      </bounds>
      <layer>-1</layer>
      <hideInbound>false</hideInbound>
      <addResultToRunContext>false</addResultToRunContext>
      <isCriticalStep>false</isCriticalStep>
      <isNonBlocking>false</isNonBlocking>
      <isParallelStep>false</isParallelStep>
      <isSingleResponse>false</isSingleResponse>
      <recordInHistory>false</recordInHistory>
      <recordRawOutput>true</recordRawOutput>
      <recordPrimaryOutput>true</recordPrimaryOutput>
      <checkPointStep>true</checkPointStep>
      <historyCheckPointStep>true</historyCheckPointStep>
      <scriptResultStep>false</scriptResultStep>
      <userPrompt></userPrompt>
      <bindings/>
      <transitions>
        <transition id="443d639e-f5aa-442c-b5c5-24bda151cfa1">
          <annotation></annotation>
          <name>return</name>
          <command>NEXT</command>
          <linkMode>false</linkMode>
          <responseSymbol>failure</responseSymbol>
          <shouldHandoff>false</shouldHandoff>
          <transitionValue>0.0</transitionValue>
          <destination>
            <refId>1f33ddc1-9218-42f5-8d19-f31bb7f014c2</refId>
          </destination>
          <source>
            <refId>1f33ddc1-9218-42f5-8d19-f31bb7f014c2</refId>
          </source>
          <positions/>
        </transition>
      </transitions>
      <properties/>
      <returnStepType>ERROR</returnStepType>
      <assignments/>
    </returnStep>
    <step id="c63beae9-2697-47a8-8c74-63b03a9b78eb">
      <annotation>5f3264e3-31cf-42a6-b825-adec27621429.c63beae9-2697-47a8-8c74-63b03a9b78eb.description</annotation>
      <name>Notify Flow Completion</name>
      <bounds>
        <x>930.0</x>
        <y>67.0</y>
      </bounds>
      <layer>-1</layer>
      <hideInbound>false</hideInbound>
      <addResultToRunContext>false</addResultToRunContext>
      <isCriticalStep>false</isCriticalStep>
      <isNonBlocking>false</isNonBlocking>
      <isParallelStep>false</isParallelStep>
      <isSingleResponse>true</isSingleResponse>
      <recordInHistory>false</recordInHistory>
      <recordRawOutput>false</recordRawOutput>
      <recordPrimaryOutput>false</recordPrimaryOutput>
      <checkPointStep>true</checkPointStep>
      <historyCheckPointStep>true</historyCheckPointStep>
      <scriptResultStep>false</scriptResultStep>
      <userPrompt></userPrompt>
      <bindings>
        <userInputBinding id="de698889-7c65-480c-abac-2efee5121f16">
          <annotation></annotation>
          <fromContextKey>CSA_PROCESS_ID</fromContextKey>
          <assignFromContext>true</assignFromContext>
          <assignToContext>false</assignToContext>
          <inputType>STRING</inputType>
          <isList>false</isList>
          <required>true</required>
          <isPersisted>true</isPersisted>
          <inputSymbol>processInstanceId</inputSymbol>
          <listDelimiter>,</listDelimiter>
          <record>false</record>
          <prompt>5f3264e3-31cf-42a6-b825-adec27621429.de698889-7c65-480c-abac-2efee5121f16.prompt</prompt>
          <isMultiSelect>false</isMultiSelect>
          <sourceDelimiter>|</sourceDelimiter>
        </userInputBinding>
        <userInputBinding id="cc2d774a-da62-40c1-9bf1-186524784a4c">
          <annotation></annotation>
          <assignFromContext>true</assignFromContext>
          <assignToContext>true</assignToContext>
          <inputType>STRING</inputType>
          <isList>false</isList>
          <required>true</required>
          <isPersisted>true</isPersisted>
          <inputSymbol>userIdentifier</inputSymbol>
          <listDelimiter>,</listDelimiter>
          <record>false</record>
          <prompt>5f3264e3-31cf-42a6-b825-adec27621429.cc2d774a-da62-40c1-9bf1-186524784a4c.prompt</prompt>
          <isMultiSelect>false</isMultiSelect>
          <sourceDelimiter>|</sourceDelimiter>
        </userInputBinding>
        <staticBinding id="8932a184-0b4a-41f5-a47f-09f632333ce0">
          <annotation></annotation>
          <assignFromContext>false</assignFromContext>
          <assignToContext>false</assignToContext>
          <inputType>STRING</inputType>
          <isList>false</isList>
          <required>true</required>
          <isPersisted>true</isPersisted>
          <inputSymbol>processInstanceState</inputSymbol>
          <listDelimiter>,</listDelimiter>
          <value>COMPLETED</value>
          <record>false</record>
        </staticBinding>
        <staticBinding id="98f168bc-0404-4f23-9f12-73052e6e6025">
          <annotation></annotation>
          <assignFromContext>false</assignFromContext>
          <assignToContext>false</assignToContext>
          <inputType>STRING</inputType>
          <isList>false</isList>
          <required>false</required>
          <isPersisted>true</isPersisted>
          <inputSymbol>processReturnCode</inputSymbol>
          <listDelimiter>,</listDelimiter>
          <value>SUCCESS</value>
          <record>false</record>
        </staticBinding>
        <staticBinding id="2ff6aba2-ca23-4379-a901-0d63f046eb66">
          <annotation></annotation>
          <assignFromContext>true</assignFromContext>
          <assignToContext>true</assignToContext>
          <inputType>STRING</inputType>
          <isList>false</isList>
          <required>false</required>
          <isPersisted>true</isPersisted>
          <inputSymbol>processStatus</inputSymbol>
          <listDelimiter>,</listDelimiter>
          <value>Flow completed successfully</value>
          <record>false</record>
        </staticBinding>
      </bindings>
      <transitions>
        <transition id="73b1afac-00d1-4763-9df1-cbfe892a67b9">
          <annotation></annotation>
          <name>done</name>
          <command>NEXT</command>
          <linkMode>false</linkMode>
          <responseSymbol>done</responseSymbol>
          <shouldHandoff>false</shouldHandoff>
          <transitionValue>0.0</transitionValue>
          <destination>
            <refId>c5964227-e3bc-44a4-8371-16464abfb13b</refId>
          </destination>
          <source>
            <refId>c63beae9-2697-47a8-8c74-63b03a9b78eb</refId>
          </source>
          <positions>
            <point>
              <x>1133.0</x>
              <y>292.0</y>
            </point>
            <point>
              <x>1128.0</x>
              <y>108.0</y>
            </point>
          </positions>
          <labelPosition>
            <x>333.0</x>
            <y>0.0</y>
          </labelPosition>
        </transition>
      </transitions>
      <properties/>
      <opRef>
        <refId>7bda02d2-425f-42aa-9ad3-5192b0fe6446</refId>
      </opRef>
      <assignments/>
      <throttleSize>0</throttleSize>
    </step>
    <step id="1b4d53a4-0b74-4fbb-bf54-b2b3fea071c4">
      <annotation>5f3264e3-31cf-42a6-b825-adec27621429.1b4d53a4-0b74-4fbb-bf54-b2b3fea071c4.description</annotation>
      <name>Notify Error</name>
      <bounds>
        <x>492.0</x>
        <y>263.0</y>
      </bounds>
      <layer>-1</layer>
      <hideInbound>false</hideInbound>
      <addResultToRunContext>false</addResultToRunContext>
      <isCriticalStep>false</isCriticalStep>
      <isNonBlocking>false</isNonBlocking>
      <isParallelStep>false</isParallelStep>
      <isSingleResponse>true</isSingleResponse>
      <recordInHistory>false</recordInHistory>
      <recordRawOutput>false</recordRawOutput>
      <recordPrimaryOutput>false</recordPrimaryOutput>
      <checkPointStep>true</checkPointStep>
      <historyCheckPointStep>true</historyCheckPointStep>
      <scriptResultStep>false</scriptResultStep>
      <userPrompt></userPrompt>
      <bindings>
        <userInputBinding id="c7383804-b394-4c91-bc90-b42a2d188749">
          <annotation></annotation>
          <fromContextKey>CSA_PROCESS_ID</fromContextKey>
          <assignFromContext>true</assignFromContext>
          <assignToContext>false</assignToContext>
          <inputType>STRING</inputType>
          <isList>false</isList>
          <required>true</required>
          <isPersisted>true</isPersisted>
          <inputSymbol>processInstanceId</inputSymbol>
          <listDelimiter>,</listDelimiter>
          <record>false</record>
          <prompt>5f3264e3-31cf-42a6-b825-adec27621429.c7383804-b394-4c91-bc90-b42a2d188749.prompt</prompt>
          <isMultiSelect>false</isMultiSelect>
          <sourceDelimiter>|</sourceDelimiter>
        </userInputBinding>
        <userInputBinding id="60a11f3f-f75d-446d-aa16-49dd39c62db8">
          <annotation></annotation>
          <assignFromContext>true</assignFromContext>
          <assignToContext>true</assignToContext>
          <inputType>STRING</inputType>
          <isList>false</isList>
          <required>true</required>
          <isPersisted>true</isPersisted>
          <inputSymbol>userIdentifier</inputSymbol>
          <listDelimiter>,</listDelimiter>
          <record>false</record>
          <prompt>5f3264e3-31cf-42a6-b825-adec27621429.60a11f3f-f75d-446d-aa16-49dd39c62db8.prompt</prompt>
          <isMultiSelect>false</isMultiSelect>
          <sourceDelimiter>|</sourceDelimiter>
        </userInputBinding>
        <staticBinding id="39903c5b-c6df-4a8b-aee4-fd0519305cb5">
          <annotation></annotation>
          <assignFromContext>false</assignFromContext>
          <assignToContext>false</assignToContext>
          <inputType>STRING</inputType>
          <isList>false</isList>
          <required>true</required>
          <isPersisted>true</isPersisted>
          <inputSymbol>processInstanceState</inputSymbol>
          <listDelimiter>,</listDelimiter>
          <value>COMPLETED</value>
          <record>false</record>
        </staticBinding>
        <staticBinding id="f5d1444a-c957-4d1e-8328-9c37b1e60e43">
          <annotation></annotation>
          <assignFromContext>false</assignFromContext>
          <assignToContext>false</assignToContext>
          <inputType>STRING</inputType>
          <isList>false</isList>
          <required>false</required>
          <isPersisted>true</isPersisted>
          <inputSymbol>processReturnCode</inputSymbol>
          <listDelimiter>,</listDelimiter>
          <value>FAILURE</value>
          <record>false</record>
        </staticBinding>
        <staticBinding id="a395d483-7cfb-4b2d-820c-e25f5b94468e">
          <annotation></annotation>
          <fromContextKey>FailureMessage</fromContextKey>
          <assignFromContext>true</assignFromContext>
          <assignToContext>true</assignToContext>
          <inputType>STRING</inputType>
          <isList>false</isList>
          <required>false</required>
          <isPersisted>true</isPersisted>
          <inputSymbol>processStatus</inputSymbol>
          <listDelimiter>,</listDelimiter>
          <value>Flow execution failed</value>
          <record>false</record>
        </staticBinding>
      </bindings>
      <transitions>
        <transition id="1d37a61f-9a2c-4ca4-9d4b-673aacba3b99">
          <annotation></annotation>
          <name>done</name>
          <command>NEXT</command>
          <linkMode>false</linkMode>
          <responseSymbol>done</responseSymbol>
          <shouldHandoff>false</shouldHandoff>
          <transitionValue>0.0</transitionValue>
          <destination>
            <refId>1f33ddc1-9218-42f5-8d19-f31bb7f014c2</refId>
          </destination>
          <source>
            <refId>1b4d53a4-0b74-4fbb-bf54-b2b3fea071c4</refId>
          </source>
          <positions>
            <point>
              <x>393.0</x>
              <y>265.0</y>
            </point>
            <point>
              <x>282.0</x>
              <y>54.0</y>
            </point>
          </positions>
          <labelPosition>
            <x>333.0</x>
            <y>0.0</y>
          </labelPosition>
        </transition>
      </transitions>
      <properties/>
      <opRef>
        <refId>7bda02d2-425f-42aa-9ad3-5192b0fe6446</refId>
      </opRef>
      <assignments/>
      <throttleSize>0</throttleSize>
    </step>
    <step id="0f9f8502-c376-4d39-ad16-ce475779b063">
      <annotation>5f3264e3-31cf-42a6-b825-adec27621429.0f9f8502-c376-4d39-ad16-ce475779b063.description</annotation>
      <name>Get Server Properties</name>
      <bounds>
        <x>86.0</x>
        <y>482.0</y>
      </bounds>
      <layer>-1</layer>
      <hideInbound>false</hideInbound>
      <addResultToRunContext>false</addResultToRunContext>
      <isCriticalStep>false</isCriticalStep>
      <isNonBlocking>false</isNonBlocking>
      <isParallelStep>false</isParallelStep>
      <isSingleResponse>false</isSingleResponse>
      <recordInHistory>false</recordInHistory>
      <recordRawOutput>false</recordRawOutput>
      <recordPrimaryOutput>false</recordPrimaryOutput>
      <checkPointStep>true</checkPointStep>
      <historyCheckPointStep>true</historyCheckPointStep>
      <scriptResultStep>false</scriptResultStep>
      <userPrompt></userPrompt>
      <bindings>
        <userInputBinding id="1c550294-78d4-4ad6-9eec-028148d6c08f">
          <annotation></annotation>
          <fromContextKey>CSA_CONTEXT_ID</fromContextKey>
          <assignFromContext>true</assignFromContext>
          <assignToContext>true</assignToContext>
          <inputType>STRING</inputType>
          <isList>false</isList>
          <required>true</required>
          <isPersisted>true</isPersisted>
          <inputSymbol>artifactId</inputSymbol>
          <listDelimiter>,</listDelimiter>
          <record>false</record>
          <prompt></prompt>
          <isMultiSelect>false</isMultiSelect>
          <sourceDelimiter>|</sourceDelimiter>
        </userInputBinding>
        <userInputBinding id="3358f7c2-1c36-45a6-9d7a-607a68c459fa">
          <annotation></annotation>
          <assignFromContext>true</assignFromContext>
          <assignToContext>true</assignToContext>
          <inputType>STRING</inputType>
          <isList>false</isList>
          <required>true</required>
          <isPersisted>true</isPersisted>
          <inputSymbol>userIdentifier</inputSymbol>
          <listDelimiter>,</listDelimiter>
          <record>false</record>
          <prompt>5f3264e3-31cf-42a6-b825-adec27621429.3358f7c2-1c36-45a6-9d7a-607a68c459fa.prompt</prompt>
          <isMultiSelect>false</isMultiSelect>
          <sourceDelimiter>|</sourceDelimiter>
        </userInputBinding>
        <staticBinding id="29319359-905f-41c6-b8e1-cfab29cde84d">
          <annotation></annotation>
          <assignFromContext>false</assignFromContext>
          <assignToContext>false</assignToContext>
          <inputType>STRING</inputType>
          <isList>false</isList>
          <required>false</required>
          <isPersisted>true</isPersisted>
          <inputSymbol>propertyNames</inputSymbol>
          <listDelimiter>,</listDelimiter>
          <value>ipAddress|hostName|publicKey</value>
          <record>false</record>
        </staticBinding>
      </bindings>
      <transitions>
        <transition id="886d18fd-f36a-4259-a3c3-aafdb7cced50">
          <annotation></annotation>
          <name>success</name>
          <command>NEXT</command>
          <linkMode>false</linkMode>
          <responseSymbol>success</responseSymbol>
          <shouldHandoff>false</shouldHandoff>
          <transitionValue>0.0</transitionValue>
          <destination>
            <refId>ed767c64-46fc-4687-8972-9c5b9a4dba9e</refId>
          </destination>
          <source>
            <refId>0f9f8502-c376-4d39-ad16-ce475779b063</refId>
          </source>
          <positions>
            <point>
              <x>136.0</x>
              <y>516.0</y>
            </point>
            <point>
              <x>311.0</x>
              <y>510.0</y>
            </point>
          </positions>
          <labelPosition>
            <x>333.0</x>
            <y>0.0</y>
          </labelPosition>
        </transition>
        <transition id="1ec2ed77-9f58-4f15-a443-41f2dc68eca8">
          <annotation></annotation>
          <name>failure</name>
          <command>NEXT</command>
          <linkMode>false</linkMode>
          <responseSymbol>failure</responseSymbol>
          <shouldHandoff>false</shouldHandoff>
          <transitionValue>0.0</transitionValue>
          <destination>
            <refId>1b4d53a4-0b74-4fbb-bf54-b2b3fea071c4</refId>
          </destination>
          <source>
            <refId>0f9f8502-c376-4d39-ad16-ce475779b063</refId>
          </source>
          <positions>
            <point>
              <x>136.0</x>
              <y>516.0</y>
            </point>
            <point>
              <x>542.0</x>
              <y>297.0</y>
            </point>
          </positions>
          <labelPosition>
            <x>333.0</x>
            <y>0.0</y>
          </labelPosition>
        </transition>
      </transitions>
      <properties/>
      <opRef>
        <refId>299ef3d3-42ca-4c36-8c0e-46ade1e339f5</refId>
      </opRef>
      <assignments>
        <flowVariableAssignment id="8090e033-f18d-4fb9-88b0-70d66a3b66e5">
          <annotation></annotation>
          <name>assignment</name>
          <action>OVERWRITE</action>
          <assignmentTargetType>FLOW_VARIABLE</assignmentTargetType>
          <contextKey>ipAddress</contextKey>
          <expression id="8777920a-5afd-4d62-972b-f249dd364784">
            <annotation></annotation>
            <name>Result Field: propertyNameValuesList</name>
            <fieldName>propertyNameValuesList</fieldName>
            <sourceType>RAWRESULT</sourceType>
            <filters>
              <stripTrailingFilter id="bfc6ab62-49e1-4b39-b063-1e3d9cd18845">
                <annotation></annotation>
                <name>Strip</name>
                <strip>ipAddress;</strip>
                <type>ALL_CHARACTERS_UP_TO_AND_INCLUDING</type>
              </stripTrailingFilter>
              <stripTrailingFilter id="b3055ecf-7c47-4e10-8b2d-c91655d1161f">
                <annotation></annotation>
                <name>Strip</name>
                <strip>|</strip>
                <type>ALL_CHARACTERS_AFTER_AND_INCLUDING</type>
              </stripTrailingFilter>
            </filters>
          </expression>
        </flowVariableAssignment>
        <flowVariableAssignment id="6fd9a666-302c-4516-b74b-10443b7952ef">
          <annotation></annotation>
          <name>assignment</name>
          <action>OVERWRITE</action>
          <assignmentTargetType>FLOW_VARIABLE</assignmentTargetType>
          <contextKey>hostName</contextKey>
          <expression id="d95f2575-61b5-444c-9566-31ac2932d3e1">
            <annotation></annotation>
            <name>Result Field: propertyNameValuesList</name>
            <fieldName>propertyNameValuesList</fieldName>
            <sourceType>RAWRESULT</sourceType>
            <filters>
              <stripTrailingFilter id="54cb177b-6f6d-41d5-8d3d-3b5d9c3dc61b">
                <annotation></annotation>
                <name>Strip</name>
                <strip>hostName;</strip>
                <type>ALL_CHARACTERS_UP_TO_AND_INCLUDING</type>
              </stripTrailingFilter>
              <stripTrailingFilter id="6b1be844-fac1-4e30-9f19-4561eb88e912">
                <annotation></annotation>
                <name>Strip</name>
                <strip>|</strip>
                <type>ALL_CHARACTERS_AFTER_AND_INCLUDING</type>
              </stripTrailingFilter>
            </filters>
          </expression>
        </flowVariableAssignment>
        <flowVariableAssignment id="98d79c84-14ff-4e99-809e-d7833df507ac">
          <annotation></annotation>
          <name>assignment</name>
          <action>OVERWRITE</action>
          <assignmentTargetType>FLOW_VARIABLE</assignmentTargetType>
          <contextKey>keyValidation</contextKey>
          <expression id="3fc29cf5-cb2d-4d1d-8d8b-25c1fb46385a">
            <annotation></annotation>
            <name>Result Field: propertyNameValuesList</name>
            <fieldName>propertyNameValuesList</fieldName>
            <sourceType>RAWRESULT</sourceType>
            <filters>
              <stripTrailingFilter id="3a6a5cf8-792a-4f2f-ac9a-5be68074def4">
                <annotation></annotation>
                <name>Strip</name>
                <strip>publicKey;</strip>
                <type>ALL_CHARACTERS_UP_TO_AND_INCLUDING</type>
              </stripTrailingFilter>
              <stripTrailingFilter id="9286acc2-d628-474d-a994-36ecf902aa16">
                <annotation></annotation>
                <name>Strip</name>
                <strip>|</strip>
                <type>ALL_CHARACTERS_AFTER_AND_INCLUDING</type>
              </stripTrailingFilter>
            </filters>
          </expression>
        </flowVariableAssignment>
      </assignments>
      <throttleSize>0</throttleSize>
    </step>
  </steps>
  <startSteps>2228153e-0cd2-4645-b03b-e33d1710ecdb</startSteps>
</flow>